setup.py
kdbase/__init__.py
kdbase/cat_helper.py
kdbase/child.py
kdbase/hbase_kv_util.py
kdbase/hbase_util.py
kdbase/hbase_util_local.py
kdbase/hbase_util_thrift.py
kdbase/hdfs.py
kdbase/hdfs_util.py
kdbase/kd_exception.py
kdbase/kd_pipe.py
kdbase/klog.py
kdbase/log.py
kdbase/opt.py
kdbase/proc_pool.py
kdbase/pyhdfs.py
kdbase/result_info.py
kdbase/service_config.py
kdbase/singleton.py
kdbase/test.py
kdbase/timer.py
kdbase/util.py
kdbase.egg-info/PKG-INFO
kdbase.egg-info/SOURCES.txt
kdbase.egg-info/dependency_links.txt
kdbase.egg-info/requires.txt
kdbase.egg-info/top_level.txt
kdbase/unittests/__init__.py
kdbase/unittests/run_test.py
kdbase/unittests/test_hbase_kv_util.py
kdbase/unittests/test_hbase_util_local.py
kdbase/unittests/test_hbase_util_thrift.py
kdbase/unittests/test_hdfs.py
kdbase/unittests/test_opt.py