Metadata-Version: 1.0
Name: kdbase
Version: 3.1.3.7
Summary: Custom script
Home-page: http://songyanjing@git.kuandeng.com/scm/tin/bigdata_support.git
Author: dq
Author-email: duquan@kuandeng.com
License: MIT Licence
Keywords: pip,kdbase,featureextraction
Platform: any
